farmOS/__init__.py
farmOS/client.py
farmOS/client_2.py
farmOS/session.py
farmOS/subrequests.py
tests/__init__.py
tests/conftest.py
farmOS-1.0.1.dist-info/LICENSE
farmOS-1.0.1.dist-info/METADATA
farmOS-1.0.1.dist-info/WHEEL
farmOS-1.0.1.dist-info/top_level.txt
farmOS-1.0.1.dist-info/RECORD
