Metadata-Version: 2.1
Name: farmOS
Version: 1.0.1
Summary: A Python library for interacting with farmOS over API. 
Home-page: https://github.com/farmOS/farmOS.py
Author: farmOS team
Author-email: mike@mstenta.net
Classifier: Programming Language :: Python :: 3
Classifier: License :: OSI Approved :: GNU General Public License v3 (GPLv3)
Classifier: Operating System :: OS Independent
Requires-Python: >=3.8
License-File: LICENSE
Requires-Dist: requests-oauthlib (~=1.3.1)
Requires-Dist: pydantic (~=1.7.3)
